{
  "positions": {
    "EKiAKACA": {
      "t": "V Mate",
      "g": [
        "Letters"
      ]
    },
    "EgqAIICA": {
      "t": "T Mate",
      "g": [
        "Letters"
      ]
    },
    "GgqAIIAACA": {
      "t": "Y Mate",
      "g": [
        "Letters"
      ]
    },
    "GAigIAgACAAg": {
      "t": "L Mate",
      "g": [
        "Letters"
      ]
    },
    "EgqAIgCA": {
      "t": "Closed Scissors Mate",
      "g": [
        "Scissors"
      ]
    },
    "EAigICiA": {
      "t": "Open Scissors Mate",
      "g": [
        "Scissors"
      ]
    },
    "GgqgAig": {
      "t": "Double Is Mate",
      "g": [
        "Towers"
      ]
    },
    "GKCgICgAAIA": {
      "t": "Twin Towers Mate",
      "g": [
        "Towers",
        "Potentially Impossible"
      ]
    },
    "GKCgIAgAAIAg": {
      "t": "Skewed Towers Mate",
      "g": [
        "Towers",
        "Potentially Impossible"
      ]
    },
    "IIAgIAgAAIAgAAAAIAg": {
      "t": "Lightning Towers Mate",
      "g": [
        "Towers",
        "Potentially Impossible"
      ]
    }
  }
}
